{
  "equivalence_card_sets": [
    [
      {
        "label": "guitar",
        "category": "item",
        "unique": true,
        "sounds": [
          "instruments/guitar1.mp3"
        ],
        "nameSound": "",
        "images": [
          "instruments/instrument_questionmark1.png",
          "instruments/instrument_questionmark2.png"
        ],
        "descriptiveSounds": [
        ]
      },
      {
        "label": "guitar_name",
        "category": "item_name",
        "unique": true,
        "sounds": [
          "instrument_names/guitar.wav"
        ],
        "nameSound": "",
        "images": [
          "instrument_names/guitar1.png",
          "instrument_names/guitar2.png"
        ],
        "descriptiveSounds": [
        ]
      }
    ],
    [
      {
        "label": "violin",
        "category": "item",
        "unique": true,
        "sounds": [
          "instruments/violin1.mp3"
        ],
        "nameSound": "",
        "images": [
          "instruments/instrument_questionmark1.png",
          "instruments/instrument_questionmark2.png"
        ],
        "descriptiveSounds": [
        ]
      },
      {
        "label": "violin_name",
        "category": "item_name",
        "unique": true,
        "sounds": [
          "instrument_names/violin.wav"
        ],
        "nameSound": "",
        "images": [
          "instrument_names/violin1.png",
          "instrument_names/violin2.png"
        ],
        "descriptiveSounds": [
        ]
      }
    ],
    [
      {
        "label": "harp",
        "category": "item",
        "unique": true,
        "sounds": [
          "instruments/harp1.mp3"
        ],
        "nameSound": "",
        "images": [
          "instruments/instrument_questionmark1.png",
          "instruments/instrument_questionmark2.png"
        ],
        "descriptiveSounds": [
        ]
      },
      {
        "label": "harp_name",
        "category": "item_name",
        "unique": true,
        "sounds": [
          "instrument_names/harp.wav"
        ],
        "nameSound": "",
        "images": [
          "instrument_names/harp1.png",
          "instrument_names/harp2.png"
        ],
        "descriptiveSounds": [
        ]
      }
    ],
    [
      {
        "label": "cello",
        "category": "item",
        "unique": true,
        "sounds": [
          "instruments/cello1.mp3"
        ],
        "nameSound": "",
        "images": [
          "instruments/instrument_questionmark1.png",
          "instruments/instrument_questionmark2.png"
        ],
        "descriptiveSounds": [
        ]
      },
      {
        "label": "cello_name",
        "category": "item_name",
        "unique": true,
        "sounds": [
          "instrument_names/cello.wav"
        ],
        "nameSound": "",
        "images": [
          "instrument_names/cello1.png",
          "instrument_names/cello2.png"
        ],
        "descriptiveSounds": [
        ]
      }
    ],
    [
      {
        "label": "flute",
        "category": "item",
        "unique": true,
        "sounds": [
          "instruments/flute1.mp3"
        ],
        "nameSound": "",
        "images": [
          "instruments/instrument_questionmark1.png",
          "instruments/instrument_questionmark2.png"
        ],
        "descriptiveSounds": [
        ]
      },
      {
        "label": "flute_name",
        "category": "item_name",
        "unique": true,
        "sounds": [
          "instrument_names/flute.wav"
        ],
        "nameSound": "",
        "images": [
          "instrument_names/flute1.png",
          "instrument_names/flute2.png"
        ],
        "descriptiveSounds": [
        ]
      }
    ],
    [
      {
        "label": "clarinet",
        "category": "item",
        "unique": true,
        "sounds": [
          "instruments/clarinet1.mp3"
        ],
        "nameSound": "",
        "images": [
          "instruments/instrument_questionmark1.png",
          "instruments/instrument_questionmark2.png"
        ],
        "descriptiveSounds": [
        ]
      },
      {
        "label": "clarinet_name",
        "category": "item_name",
        "unique": true,
        "sounds": [
          "instrument_names/clarinet.wav"
        ],
        "nameSound": "",
        "images": [
          "instrument_names/clarinet1.png",
          "instrument_names/clarinet2.png"
        ],
        "descriptiveSounds": [
        ]
      }
    ],
    [
      {
        "label": "oboe",
        "category": "item",
        "unique": true,
        "sounds": [
          "instruments/oboe1.mp3"
        ],
        "nameSound": "",
        "images": [
          "instruments/instrument_questionmark1.png",
          "instruments/instrument_questionmark2.png"
        ],
        "descriptiveSounds": [
        ]
      },
      {
        "label": "oboe_name",
        "category": "item_name",
        "unique": true,
        "sounds": [
          "instrument_names/oboe.wav"
        ],
        "nameSound": "",
        "images": [
          "instrument_names/oboe1.png",
          "instrument_names/oboe2.png"
        ],
        "descriptiveSounds": [
        ]
      }
    ],
    [
      {
        "label": "trumpet",
        "category": "item",
        "unique": true,
        "sounds": [
          "instruments/trumpet1.mp3"
        ],
        "nameSound": "",
        "images": [
          "instruments/instrument_questionmark1.png",
          "instruments/instrument_questionmark2.png"
        ],
        "descriptiveSounds": [
        ]
      },
      {
        "label": "trumpet_name",
        "category": "item_name",
        "unique": true,
        "sounds": [
          "instrument_names/trumpet.wav"
        ],
        "nameSound": "",
        "images": [
          "instrument_names/trumpet1.png",
          "instrument_names/trumpet2.png"
        ],
        "descriptiveSounds": [
        ]
      }
    ],
    [
      {
        "label": "trombone",
        "category": "item",
        "unique": true,
        "sounds": [
          "instruments/trombone1.mp3"
        ],
        "nameSound": "",
        "images": [
          "instruments/instrument_questionmark1.png",
          "instruments/instrument_questionmark2.png"
        ],
        "descriptiveSounds": [
        ]
      },
      {
        "label": "trombone_name",
        "category": "item_name",
        "unique": true,
        "sounds": [
          "instrument_names/trombone.wav"
        ],
        "nameSound": "",
        "images": [
          "instrument_names/trombone1.png",
          "instrument_names/trombone2.png"
        ],
        "descriptiveSounds": [
        ]
      }
    ],
    [
      {
        "label": "timpani",
        "category": "item",
        "unique": true,
        "sounds": [
          "instruments/timpani1.mp3"
        ],
        "nameSound": "",
        "images": [
          "instruments/instrument_questionmark1.png",
          "instruments/instrument_questionmark2.png"
        ],
        "descriptiveSounds": [
        ]
      },
      {
        "label": "timpani_name",
        "category": "item_name",
        "unique": true,
        "sounds": [
          "instrument_names/timpani.wav"
        ],
        "nameSound": "",
        "images": [
          "instrument_names/timpani1.png",
          "instrument_names/timpani2.png"
        ],
        "descriptiveSounds": [
        ]
      }
    ],
    [
      {
        "label": "snare",
        "category": "item",
        "unique": true,
        "sounds": [
          "instruments/snare1.mp3"
        ],
        "nameSound": "",
        "images": [
          "instruments/instrument_questionmark1.png",
          "instruments/instrument_questionmark2.png"
        ],
        "descriptiveSounds": [
        ]
      },
      {
        "label": "snare_name",
        "category": "item_name",
        "unique": true,
        "sounds": [
          "instrument_names/snare.wav"
        ],
        "nameSound": "",
        "images": [
          "instrument_names/snare1.png",
          "instrument_names/snare2.png"
        ],
        "descriptiveSounds": [
        ]
      }
    ],
    [
      {
        "label": "xylophone",
        "category": "item",
        "unique": true,
        "sounds": [
          "instruments/xylophone1.mp3"
        ],
        "nameSound": "",
        "images": [
          "instruments/instrument_questionmark1.png",
          "instruments/instrument_questionmark2.png"
        ],
        "descriptiveSounds": [
        ]
      },
      {
        "label": "xylophone_name",
        "category": "item_name",
        "unique": true,
        "sounds": [
          "instrument_names/xylophone.wav"
        ],
        "nameSound": "",
        "images": [
          "instrument_names/xylophone1.png",
          "instrument_names/xylophone2.png"
        ],
        "descriptiveSounds": [
        ]
      }
    ],
    [
      {
        "label": "cymbal",
        "category": "item",
        "unique": true,
        "sounds": [
          "instruments/cymbal1.mp3"
        ],
        "nameSound": "",
        "images": [
          "instruments/instrument_questionmark1.png",
          "instruments/instrument_questionmark2.png"
        ],
        "descriptiveSounds": [
        ]
      },
      {
        "label": "cymbal_name",
        "category": "item_name",
        "unique": true,
        "sounds": [
          "instrument_names/cymbal.wav"
        ],
        "nameSound": "",
        "images": [
          "instrument_names/cymbal1.png",
          "instrument_names/cymbal2.png"
        ],
        "descriptiveSounds": [
        ]
      }
    ],
    [
      {
        "label": "piano",
        "category": "item",
        "unique": true,
        "sounds": [
          "instruments/piano1.mp3"
        ],
        "nameSound": "",
        "images": [
          "instruments/instrument_questionmark1.png",
          "instruments/instrument_questionmark2.png"
        ],
        "descriptiveSounds": [
        ]
      },
      {
        "label": "piano_name",
        "category": "item_name",
        "unique": true,
        "sounds": [
          "instrument_names/piano.wav"
        ],
        "nameSound": "",
        "images": [
          "instrument_names/piano1.png",
          "instrument_names/piano2.png"
        ],
        "descriptiveSounds": [
        ]
      }
    ],
    [
      {
        "label": "cembalo",
        "category": "item",
        "unique": true,
        "sounds": [
          "instruments/cembalo1.mp3"
        ],
        "nameSound": "",
        "images": [
          "instruments/instrument_questionmark1.png",
          "instruments/instrument_questionmark2.png"
        ],
        "descriptiveSounds": [
        ]
      },
      {
        "label": "cembalo_name",
        "category": "item_name",
        "unique": true,
        "sounds": [
          "instrument_names/cembalo.wav"
        ],
        "nameSound": "",
        "images": [
          "instrument_names/cembalo1.png",
          "instrument_names/cembalo2.png"
        ],
        "descriptiveSounds": [
        ]
      }
    ],
    [
      {
        "label": "organ",
        "category": "item",
        "unique": true,
        "sounds": [
          "instruments/organ1.mp3"
        ],
        "nameSound": "",
        "images": [
          "instruments/instrument_questionmark1.png",
          "instruments/instrument_questionmark2.png"
        ],
        "descriptiveSounds": [
        ]
      },
      {
        "label": "organ_name",
        "category": "item_name",
        "unique": true,
        "sounds": [
          "instrument_names/organ.wav"
        ],
        "nameSound": "",
        "images": [
          "instrument_names/organ1.png",
          "instrument_names/organ2.png"
        ],
        "descriptiveSounds": [
        ]
      }
    ],
    [
      {
        "label": "double-bass",
        "category": "item",
        "unique": true,
        "sounds": [
          "instruments/double-bass1.mp3"
        ],
        "nameSound": "",
        "images": [
          "instruments/instrument_questionmark1.png",
          "instruments/instrument_questionmark2.png"
        ],
        "descriptiveSounds": [
        ]
      },
      {
        "label": "double-bass_name",
        "category": "item_name",
        "unique": true,
        "sounds": [
          "instrument_names/double-bass.wav"
        ],
        "nameSound": "",
        "images": [
          "instrument_names/double-bass1.png",
          "instrument_names/double-bass2.png"
        ],
        "descriptiveSounds": [
        ]
      }
    ],
    [
      {
        "label": "fagotto",
        "category": "item",
        "unique": true,
        "sounds": [
          "instruments/fagotto1.mp3"
        ],
        "nameSound": "",
        "images": [
          "instruments/instrument_questionmark1.png",
          "instruments/instrument_questionmark2.png"
        ],
        "descriptiveSounds": [
        ]
      },
      {
        "label": "fagotto_name",
        "category": "item_name",
        "unique": true,
        "sounds": [
          "instrument_names/fagotto.wav"
        ],
        "nameSound": "",
        "images": [
          "instrument_names/fagotto1.png",
          "instrument_names/fagotto2.png"
        ],
        "descriptiveSounds": [
        ]
      }
    ],
    [
      {
        "label": "saxophone",
        "category": "item",
        "unique": true,
        "sounds": [
          "instruments/saxophone1.mp3"
        ],
        "nameSound": "",
        "images": [
          "instruments/instrument_questionmark1.png",
          "instruments/instrument_questionmark2.png"
        ],
        "descriptiveSounds": [
        ]
      },
      {
        "label": "saxophone_name",
        "category": "item_name",
        "unique": true,
        "sounds": [
          "instrument_names/saxophone.wav"
        ],
        "nameSound": "",
        "images": [
          "instrument_names/saxophone1.png",
          "instrument_names/saxophone2.png"
        ],
        "descriptiveSounds": [
        ]
      }
    ],
    [
      {
        "label": "french-horn",
        "category": "item",
        "unique": true,
        "sounds": [
          "instruments/french-horn1.mp3"
        ],
        "nameSound": "",
        "images": [
          "instruments/instrument_questionmark1.png",
          "instruments/instrument_questionmark2.png"
        ],
        "descriptiveSounds": [
        ]
      },
      {
        "label": "french-horn_name",
        "category": "item_name",
        "unique": true,
        "sounds": [
          "instrument_names/french-horn.wav"
        ],
        "nameSound": "",
        "images": [
          "instrument_names/french-horn1.png",
          "instrument_names/french-horn2.png"
        ],
        "descriptiveSounds": [
        ]
      }
    ],
    [
      {
        "label": "tuba",
        "category": "item",
        "unique": true,
        "sounds": [
          "instruments/tuba1.mp3"
        ],
        "nameSound": "",
        "images": [
          "instruments/instrument_questionmark1.png",
          "instruments/instrument_questionmark2.png"
        ],
        "descriptiveSounds": [
        ]
      },
      {
        "label": "tuba_name",
        "category": "item_name",
        "unique": true,
        "sounds": [
          "instrument_names/tuba.wav"
        ],
        "nameSound": "",
        "images": [
          "instrument_names/tuba1.png",
          "instrument_names/tuba2.png"
        ],
        "descriptiveSounds": [
        ]
      }
    ],
    [
      {
        "label": "glockenspiel",
        "category": "item",
        "unique": true,
        "sounds": [
          "instruments/glockenspiel1.mp3"
        ],
        "nameSound": "",
        "images": [
          "instruments/instrument_questionmark1.png",
          "instruments/instrument_questionmark2.png"
        ],
        "descriptiveSounds": [
        ]
      },
      {
        "label": "glockenspiel_name",
        "category": "item_name",
        "unique": true,
        "sounds": [
          "instrument_names/glockenspiel.wav"
        ],
        "nameSound": "",
        "images": [
          "instrument_names/glockenspiel1.png",
          "instrument_names/glockenspiel2.png"
        ],
        "descriptiveSounds": [
        ]
      }
    ],
    [
      {
        "label": "elguitar",
        "category": "item",
        "unique": true,
        "sounds": [
          "instruments/elguitar1.mp3"
        ],
        "nameSound": "",
        "images": [
          "instruments/instrument_questionmark1.png",
          "instruments/instrument_questionmark2.png"
        ],
        "descriptiveSounds": [
        ]
      },
      {
        "label": "elguitar_name",
        "category": "item_name",
        "unique": true,
        "sounds": [
          "instrument_names/elguitar.wav"
        ],
        "nameSound": "",
        "images": [
          "instrument_names/elguitar1.png",
          "instrument_names/elguitar2.png"
        ],
        "descriptiveSounds": [
        ]
      }
    ],
    [
      {
        "label": "harmonium",
        "category": "item",
        "unique": true,
        "sounds": [
          "instruments/harmonium1.mp3"
        ],
        "nameSound": "",
        "images": [
          "instruments/instrument_questionmark1.png",
          "instruments/instrument_questionmark2.png"
        ],
        "descriptiveSounds": [
        ]
      },
      {
        "label": "harmonium_name",
        "category": "item_name",
        "unique": true,
        "sounds": [
          "instrument_names/harmonium.wav"
        ],
        "nameSound": "",
        "images": [
          "instrument_names/harmonium1.png",
          "instrument_names/harmonium2.png"
        ],
        "descriptiveSounds": [
        ]
      }
    ],
    [
      {
        "label": "marimba",
        "category": "item",
        "unique": true,
        "sounds": [
          "instruments/marimba1.mp3"
        ],
        "nameSound": "",
        "images": [
          "instruments/instrument_questionmark1.png",
          "instruments/instrument_questionmark2.png"
        ],
        "descriptiveSounds": [
        ]
      },
      {
        "label": "marimba_name",
        "category": "item_name",
        "unique": true,
        "sounds": [
          "instrument_names/marimba.wav"
        ],
        "nameSound": "",
        "images": [
          "instrument_names/marimba1.png",
          "instrument_names/marimba2.png"
        ],
        "descriptiveSounds": [
        ]
      }
    ],
    [
      {
        "label": "accordion",
        "category": "item",
        "unique": true,
        "sounds": [
          "instruments/accordion1.mp3"
        ],
        "nameSound": "",
        "images": [
          "instruments/instrument_questionmark1.png",
          "instruments/instrument_questionmark2.png"
        ],
        "descriptiveSounds": [
        ]
      },
      {
        "label": "accordion_name",
        "category": "item_name",
        "unique": true,
        "sounds": [
          "instrument_names/accordion.wav"
        ],
        "nameSound": "",
        "images": [
          "instrument_names/accordion1.png",
          "instrument_names/accordion2.png"
        ],
        "descriptiveSounds": [
        ]
      }
    ],
    [
      {
        "label": "drums",
        "category": "item",
        "unique": true,
        "sounds": [
          "instruments/drums1.mp3"
        ],
        "nameSound": "",
        "images": [
          "instruments/instrument_questionmark1.png",
          "instruments/instrument_questionmark2.png"
        ],
        "descriptiveSounds": [
        ]
      },
      {
        "label": "drums_name",
        "category": "item_name",
        "unique": true,
        "sounds": [
          "instrument_names/drums.wav"
        ],
        "nameSound": "",
        "images": [
          "instrument_names/drums1.png",
          "instrument_names/drums2.png"
        ],
        "descriptiveSounds": [
        ]
      }
    ],
    [
      {
        "label": "oud",
        "category": "item",
        "unique": true,
        "sounds": [
          "instruments/oud1.mp3"
        ],
        "nameSound": "",
        "images": [
          "instruments/instrument_questionmark1.png",
          "instruments/instrument_questionmark2.png"
        ],
        "descriptiveSounds": [
        ]
      },
      {
        "label": "oud_name",
        "category": "item_name",
        "unique": true,
        "sounds": [
          "instrument_names/oud.wav"
        ],
        "nameSound": "",
        "images": [
          "instrument_names/oud1.png",
          "instrument_names/oud2.png"
        ],
        "descriptiveSounds": [
        ]
      }
    ],
    [
      {
        "label": "triangle",
        "category": "item",
        "unique": true,
        "sounds": [
          "instruments/triangle1.mp3"
        ],
        "nameSound": "",
        "images": [
          "instruments/instrument_questionmark1.png",
          "instruments/instrument_questionmark2.png"
        ],
        "descriptiveSounds": [
        ]
      },
      {
        "label": "triangle_name",
        "category": "item_name",
        "unique": true,
        "sounds": [
          "instrument_names/triangle.wav"
        ],
        "nameSound": "",
        "images": [
          "instrument_names/triangle1.png",
          "instrument_names/triangle2.png"
        ],
        "descriptiveSounds": [
        ]
      }
    ],
    [
      {
        "label": "flogera",
        "category": "item",
        "unique": true,
        "sounds": [
          "instruments/flogera1.mp3"
        ],
        "nameSound": "",
        "images": [
          "instruments/instrument_questionmark1.png",
          "instruments/instrument_questionmark2.png"
        ],
        "descriptiveSounds": [
        ]
      },
      {
        "label": "flogera_name",
        "category": "item_name",
        "unique": true,
        "sounds": [
          "instrument_names/flogera.wav"
        ],
        "nameSound": "",
        "images": [
          "instrument_names/flogera1.png",
          "instrument_names/flogera2.png"
        ],
        "descriptiveSounds": [
        ]
      }
    ]
  ]
}